[
  {
    "task_id": "ID001",
    "task_name": "bug",
    "deadline": "1 Week",
    "assign": "employe1",
    "description": ""
  },
  {
    "task_id": "ID002",
    "task_name": "bug",
    "deadline": "5 days",
    "assign": "employe4",
    "description": "Find bug"
  },
  {
    "task_id": "ada",
    "task_name": "daad",
    "deadline": "ssa",
    "assign": "employe4",
    "description": "afa"
  },
  {
    "task_id": "ID005",
    "task_name": "we",
    "deadline": "ssa",
    "assign": "employe4",
    "description": "afa"
  },
  {
    "task_id": "sa",
    "task_name": "sas",
    "deadline": "saas",
    "assign": "employe2",
    "description": "sasaas"
  },
  {
    "task_id": "",
    "task_name": "",
    "deadline": "",
    "assign": "",
    "description": ""
  },
  {
    "task_id": "ID006",
    "task_name": "style",
    "deadline": "1 d",
    "assign": "employe2",
    "description": "css"
  },
  {
    "task_id": "003",
    "task_name": "sa",
    "deadline": "asas",
    "assign": "employe3",
    "description": "assa"
  },
  {
    "task_id": "sa",
    "task_name": "assa",
    "deadline": "sasa",
    "assign": "employe2",
    "description": "sasa"
  },
  {
    "task_id": "s",
    "task_name": "sa",
    "deadline": "as",
    "assign": "employe2",
    "description": "ssas"
  }
]